ad_low_noise_float_2023_decoder.cp37-win_amd64.pyd
ad_low_noise_float_2023_decoder-0.1.7.dist-info/METADATA
ad_low_noise_float_2023_decoder-0.1.7.dist-info/WHEEL
ad_low_noise_float_2023_decoder-0.1.7.dist-info/top_level.txt
ad_low_noise_float_2023_decoder-0.1.7.dist-info/RECORD
