Metadata-Version: 2.1
Name: ad-low-noise-float-2023-decoder
Version: 0.1.7
Summary: ad_low_noise_float_2023_decoder for ad_low_noise_float_2023_git
Home-page: https://github.com/petermaerki/ad_low_noise_float_2023_git/
Author: Hans Maerki
Author-email: buhtig.hans.maerki@ergoinfo.ch
Requires-Python: >=3.7.9
Requires-Dist: numpy >=1.21.1
